delumowave/__init__.py
delumowave/controller.py
delumowave/cover.py
delumowave/node.py
delumowave/relay.py
delumowave/rgb.py
delumowave/thermostat.py
delumowave/config/cover.py
delumowave/config/delumo.py
delumowave/config/node.py
delumowave/config/relay.py
delumowave/config/rgb.py
delumowave/config/thermostat.py
DelumoWave-0.1.27.dist-info/METADATA
DelumoWave-0.1.27.dist-info/WHEEL
DelumoWave-0.1.27.dist-info/top_level.txt
DelumoWave-0.1.27.dist-info/RECORD
