Metadata-Version: 2.1
Name: DelumoWave
Version: 0.1.27
Summary: API for Delumo radio controller
Home-page: https://bitbucket.org/delumo/DelumoWave
Author: Roman Alexeev
Author-email: roman@alexeyev.su
License: MIT
Platform: UNKNOWN
Classifier: Development Status :: 2 - Pre-Alpha
Classifier: License :: OSI Approved :: MIT License
Classifier: Operating System :: POSIX :: Linux
Classifier: Programming Language :: Python :: 3.6
Classifier: Topic :: Home Automation
Classifier: Topic :: System :: Hardware
Classifier: Topic :: System :: Hardware :: Hardware Drivers
Requires-Dist: pyserial (>=3.4)
